pychoacoustics/.directory
pychoacoustics/PSI_method.py
pychoacoustics/PSI_method2.py
pychoacoustics/PSI_method_est_guess.py
pychoacoustics/UML_method.py
pychoacoustics/UML_method_est_guess.py
pychoacoustics/__init__.py
pychoacoustics/__main__.py
pychoacoustics/_version_info.py
pychoacoustics/audio_manager.py
pychoacoustics/control_window.py
pychoacoustics/dialog_edit_end_message.py
pychoacoustics/dialog_edit_experimenters.py
pychoacoustics/dialog_edit_phones.py
pychoacoustics/dialog_edit_preferences.py
pychoacoustics/dialog_memory_file_parameters_differ.py
pychoacoustics/dialog_process_results.py
pychoacoustics/dialog_show_exp_doc.py
pychoacoustics/dialog_show_fortune.py
pychoacoustics/dialog_show_instructions.py
pychoacoustics/dialog_show_par_diff.py
pychoacoustics/dialog_swap_blocks.py
pychoacoustics/global_parameters.py
pychoacoustics/pyqtver.py
pychoacoustics/pysdt.py
pychoacoustics/qrc_resources.py
pychoacoustics/redirect_out.py
pychoacoustics/response_box.py
pychoacoustics/sndlib.py
pychoacoustics/stats_utils.py
pychoacoustics/utils_general.py
pychoacoustics/utils_process_results.py
pychoacoustics/utils_redirect_stream_to_file.py
pychoacoustics/wavpy.py
pychoacoustics/wavpy_sndf.py
pychoacoustics/win_PSI_est_guess_parspace_plot.py
pychoacoustics/win_PSI_parspace_plot.py
pychoacoustics/win_UML_est_guess_parspace_plot.py
pychoacoustics/win_UML_parspace_plot.py
pychoacoustics/win_categorical_plot.py
pychoacoustics/win_prog_adaptive_plot.py
pychoacoustics/win_psychometric_listener_plot.py
pychoacoustics/default_experiments/F0DL.py
pychoacoustics/default_experiments/__init__.py
pychoacoustics/default_experiments/audiogram.py
pychoacoustics/default_experiments/audiogram_mf.py
pychoacoustics/default_experiments/dummy_adaptive.py
pychoacoustics/default_experiments/dummy_adaptive_interleaved.py
pychoacoustics/default_experiments/dummy_constant.py
pychoacoustics/default_experiments/freq.py
pychoacoustics/default_experiments/lev_match.py
pychoacoustics-0.6.13.dist-info/COPYING.txt
pychoacoustics-0.6.13.dist-info/METADATA
pychoacoustics-0.6.13.dist-info/WHEEL
pychoacoustics-0.6.13.dist-info/entry_points.txt
pychoacoustics-0.6.13.dist-info/top_level.txt
pychoacoustics-0.6.13.dist-info/RECORD
