Metadata-Version: 2.1
Name: pychoacoustics
Version: 0.6.13
Summary: Python application for running psychoacoustics experiments
Author-email: Samuele Carcagno <sam.carcagno@gmail.com>
License: GNU GENERAL PUBLIC LICENSE
Project-URL: Homepage, https://samcarcagno.altervista.org/pychoacoustics/pychoacoustics.html
Project-URL: Bug Tracker, https://github.com/sam81/pychoacoustics/issues
Classifier: Programming Language :: Python :: 3
Classifier: License :: OSI Approved :: GNU General Public License v3 (GPLv3)
Classifier: Operating System :: OS Independent
Classifier: Development Status :: 4 - Beta
Classifier: Environment :: Console
Classifier: Intended Audience :: Science/Research
Classifier: Intended Audience :: Developers
Classifier: Intended Audience :: Education
Classifier: Environment :: X11 Applications :: Qt
Classifier: Intended Audience :: Developers
Classifier: Operating System :: MacOS :: MacOS X
Classifier: Operating System :: Microsoft :: Windows
Classifier: Operating System :: POSIX
Classifier: Topic :: Scientific/Engineering
Classifier: Topic :: Scientific/Engineering :: Bio-Informatics
Requires-Python: >=3.7
License-File: COPYING.txt
Requires-Dist: matplotlib >=3.0.0
Requires-Dist: numpy >=1.0.0
Requires-Dist: pandas >=1.0.0
Requires-Dist: PyAudio >=0.2.11
Requires-Dist: PyQt6 >=6.6.0
Requires-Dist: scipy >=1.0.1
Requires-Dist: pysofaconventions >=0.1.1
Provides-Extra: dev
Requires-Dist: sphinx-rtd-theme >=1.0.0 ; extra == 'dev'
